sphinx_pdf_generate/__init__.py
sphinx_pdf_generate/__main__.py
sphinx_pdf_generate/build.py
sphinx_pdf_generate/cli.py
sphinx_pdf_generate/cover.py
sphinx_pdf_generate/logging.py
sphinx_pdf_generate/options.py
sphinx_pdf_generate/pdf_generate.py
sphinx_pdf_generate/preprocessor/__init__.py
sphinx_pdf_generate/preprocessor/content/__init__.py
sphinx_pdf_generate/preprocessor/content/tabbed_block.py
sphinx_pdf_generate/preprocessor/links/__init__.py
sphinx_pdf_generate/preprocessor/links/util.py
sphinx_pdf_generate/preprocessor/prep.py
sphinx_pdf_generate/renderer.py
sphinx_pdf_generate/styles/__init__.py
sphinx_pdf_generate/styles/_paging.css
sphinx_pdf_generate/styles/cover.css
sphinx_pdf_generate/styles/toc.css
sphinx_pdf_generate/templates/__init__.py
sphinx_pdf_generate/templates/default_cover.html.j2
sphinx_pdf_generate/templates/filters/__init__.py
sphinx_pdf_generate/templates/filters/datetime.py
sphinx_pdf_generate/templates/filters/url.py
sphinx_pdf_generate/templates/template.py
sphinx_pdf_generate/themes/__init__.py
sphinx_pdf_generate/themes/alabaster.py
sphinx_pdf_generate/themes/generic.py
sphinx_pdf_generate/themes/immaterial_styles.css
sphinx_pdf_generate/themes/material_styles.css
sphinx_pdf_generate/themes/sphinx_immaterial.py
sphinx_pdf_generate/themes/sphinx_material.py
sphinx_pdf_generate/toc.py
sphinx_pdf_generate/utils.py
sphinx_pdf_generate/version.py
sphinx_pdf_generate-0.0.4.dist-info/LICENSE.md
sphinx_pdf_generate-0.0.4.dist-info/METADATA
sphinx_pdf_generate-0.0.4.dist-info/WHEEL
sphinx_pdf_generate-0.0.4.dist-info/entry_points.txt
sphinx_pdf_generate-0.0.4.dist-info/RECORD
