Metadata-Version: 2.1
Name: sphinx-pdf-generate
Version: 0.0.4
Summary: A Sphinx extension to generate individual PDF files for each documentation page.
Home-page: https://github.com/iSOLveIT/sphinx-pdf-generate
License: MIT
Author: Duodu Randy
Author-email: duodurandy19@gmail.com
Maintainer: Duodu Randy
Maintainer-email: duodurandy19@gmail.com
Requires-Python: >=3.8.0,<4.0
Classifier: Development Status :: 2 - Pre-Alpha
Classifier: Framework :: Sphinx :: Extension
Classifier: Intended Audience :: Developers
Classifier: License :: OSI Approved :: MIT License
Classifier: Operating System :: OS Independent
Classifier: Programming Language :: Python
Classifier: Programming Language :: Python :: 3
Classifier: Programming Language :: Python :: 3.8
Classifier: Programming Language :: Python :: 3.9
Classifier: Programming Language :: Python :: 3.10
Classifier: Programming Language :: Python :: 3.11
Classifier: Programming Language :: Python :: 3.12
Classifier: Topic :: Documentation :: Sphinx
Classifier: Topic :: Software Development :: Build Tools
Provides-Extra: docs
Provides-Extra: immaterial
Requires-Dist: beautifulsoup4 (>=4.6.3)
Requires-Dist: colorama (>=0.4.6)
Requires-Dist: docutils (>=0.15)
Requires-Dist: jinja2 (>=3.0.0)
Requires-Dist: pathlib (>=1.0)
Requires-Dist: pypdf (>=3.6.0)
Requires-Dist: simple-file-checksum (>=1.2.2)
Requires-Dist: sphinx (>=5.0) ; extra == "docs"
Requires-Dist: weasyprint (>=60.0,<61.0)
Project-URL: Documentation, https://isolveit.github.io/sphinx-pdf-generate/
Project-URL: Repository, https://github.com/iSOLveIT/sphinx-pdf-generate
